nhehir-0.3.0.data/scripts/quickstats
quickstats/__init__.py
quickstats/_version.py
quickstats/clis/__init__.py
quickstats/clis/core.py
quickstats/clis/inspect_ws.py
quickstats/components/__init__.py
quickstats/components/cli.py
quickstats/components/cli_parser_obsolete.py
quickstats/components/extended_minimizer.py
quickstats/components/extended_model.py
quickstats/components/inspect_ws.py
quickstats/components/likelihood.py
quickstats/components/np_ranking_plotter_obsolete.py
quickstats/components/nuisance_parameter_pull.py
quickstats/components/nuisance_parameter_pull_obsolete.py
quickstats/components/numerics.py
quickstats/components/roofit_plotter.py
quickstats/components/root_plots.py
quickstats/macros/RooTwoSidedCBShape.cxx
quickstats/macros/RooTwoSidedCBShape.h
quickstats/macros/RooTwoSidedCBShape_cxx.d
quickstats/macros/RooTwoSidedCBShape_cxx.so
quickstats/macros/RooTwoSidedCBShape_cxx_ACLiC_dict_rdict.pcm
quickstats/plots/__init__.py
quickstats/plots/core.py
quickstats/plots/likelihood_scan_plot.py
quickstats/plots/np_ranking_plot.py
quickstats/plots/template.py
quickstats/utils/__init__.py
quickstats/utils/common_utils.py
quickstats/utils/process_tools.py
quickstats/utils/root_utils.py
nhehir-0.3.0.dist-info/METADATA
nhehir-0.3.0.dist-info/WHEEL
nhehir-0.3.0.dist-info/top_level.txt
nhehir-0.3.0.dist-info/RECORD
