Metadata-Version: 2.1
Name: nhehir
Version: 0.3.0
Summary: A tool for quick statistical analysis for HEP experiments
Home-page: UNKNOWN
Author: Alkaid Cheng
Author-email: chi.lung.cheng@cern.ch
License: UNKNOWN
Platform: UNKNOWN
Classifier: Programming Language :: Python :: 3.6
Classifier: Programming Language :: Python :: 3.7
Classifier: Programming Language :: Python :: 3.8
Classifier: License :: OSI Approved :: MIT License
Classifier: Operating System :: OS Independent
Requires-Python: >=3.6
Requires-Dist: numpy
Requires-Dist: matplotlib
Requires-Dist: click
